circuitpython_simple_dial/dial_needle.py
circuitpython_simple_dial/simple_dial.py
circuitpython_simnple_dial-0.2.1.dist-info/LICENSE
circuitpython_simnple_dial-0.2.1.dist-info/METADATA
circuitpython_simnple_dial-0.2.1.dist-info/WHEEL
circuitpython_simnple_dial-0.2.1.dist-info/top_level.txt
circuitpython_simnple_dial-0.2.1.dist-info/RECORD
