Metadata-Version: 2.1
Name: circuitpython-simnple-dial
Version: 0.2.1
Summary: Simple dial widget
Author-email: "Jose D. Montoya" <simpledial@mailmeto.mozmail.com>
License: MIT
Project-URL: Homepage, https://github.com/jposada202020/CircuitPython_simple_dial.git
Keywords: adafruit,blinka,circuitpython,displayio,circuitpython,graphics,dial,library,plotting,clock
Classifier: Intended Audience :: Developers
Classifier: Topic :: Software Development :: Libraries
Classifier: Topic :: Software Development :: Embedded Systems
Classifier: Topic :: System :: Hardware
Classifier: License :: OSI Approved :: MIT License
Classifier: Programming Language :: Python :: 3
License-File: LICENSE
Requires-Dist: Adafruit-Blinka
Provides-Extra: optional
